{
    "out_of_stock": "OUT OF STOCK",
    "add": "ADD",
    "view_all": "View all",
    "categories": "Categories",
    "brands": "Brands",
    "order": "Order",
    "pending": "Pending",
    "completed": "Completed",
    "cancelled": "Cancelled",
    "nothin_to_show": "Nothing to show here",
    "name": "Name",
    "price": "Price",
    "qty": "Qty",
    "total": "Total",
    "addresses": "Addresses",
    "add_new_address": "Add new address",
    "phone_number": "Phone number",
    "first_name": "First name",
    "last_name": "Last name",
    "email": "Email",
    "update": "Update",
    "order_success_msg": "Your order was successfully placed\nThank you for shopping with us",
    "order_id": "Order id",
    "total_order_value": "Total order value",
    "delivery_address": "Delivery address",
    "delivery_date": "Delivery date",
    "delivery_time": "Delivery time",
    "payment_method": "Payment method",
    "confirm_order": "Confirm order",
    "checkout": "Checkout",
    "cod": "Cash on delivery",
    "net_banking": "Credit Card/Net Banking",
    "free": "Free",
    "my_account": "My Account",
    "settings": "Settings",
    "favorites": "Favorites",
    "support": "Support",
    "address_1": "Address 1",
    "address_2": "Address 2",
    "city": "City",
    "region": "Region",
    "address_added_success": "The address was successfully added.",
    "something_went_wrong_try_again": "Something went wrong, Please try again",
    "enter_valid_address": "Please enter a valid address.",
    "back": "Back",
    "back_to_shopping": "Back to Shopping",
    "clear_cart": "Clear cart",
    "order_place_faild": "We could not place your order, Please try again.",
    "please_register_or_login": "Please login or register before placing an order, Do you want to login now?",
    "select_your_city": "Select your city",
    "continue": "Continue",
    "about_the_company": "About the company",
    "contact_us": "Contact Us",
    "contact_text":"You can contact us by calling or sending an email",
    "call_us": "CALL US",
    "send_an_email": "SEND AN EMAIL",
    "phone": "Phone",
    "promotion": "Promotion",
    "something_went_wrong": "Something went wrong",
    "my_favorites": "My Favorites",
    "register": "Register",
    "login": "Login",
    "i_am_already_registered": "I am already registered",
    "continue_with_facebook": "Continue with Facebook",
    "i_wantitoiregister": "I want to register",
    "verification_code": "Verification code",
    "otp_sent_msg": "We have sent you a verification code to {PHONE_NO}, Type it in the box below.",
    "verify": "Verify",
    "login_success_msg": "You have been successfully logged in.",
    "form_enter_valid_name": "Please enter a valid first & last name.",
    "form_enter_valid_phone": "Please enter a valid 10 digit phone number.",
    "phone_enter_valid_otp": "Please enter a valid 6 digit verification code.",
    "delivery_timing": "Delivery timing",
    "download_invoice": "Download invoice",
    "items": "Items",
    "cancel_order_confirm": "Are you sure you want to cancel this order?",
    "cancel_order_success": "Your Order was successfully canceled.",
    "cancel_order_toolate": "We are sorry but it is too late to cancel the order.",
    "could_not_complete_action": "We could not complete the current action, Please try again.",
    "coult_not_load_order_details": "We could not load order details.",
    "order_products_by_calling": "You can order products by calling us",
    "call": "Call",
    "order_products_by_contacting_on_whatsapp": "You can order products by contacting us on WhatsApp",
    "send_a_message": "SEND A MESSAGE",
    "regular_delivery": "Regular delivery",
    "fast_delivery": "Fast delivery",
    "my_cart": "My Cart",
    "my_orders": "My Orders",
    "order_on_phone": "Order on Phone",
    "order_on_whatsapp": "Order on WhatsApp",
    "about_company": "About company",
    "products": "Products",
    "search": "Search",
    "order_details": "Order details",
    "add_address": "Add Address",
    "product": "Product",
    "account": "Account"
}